finlab_guard/__init__.py
finlab_guard/cache/__init__.py
finlab_guard/cache/manager.py
finlab_guard/core/__init__.py
finlab_guard/core/guard.py
finlab_guard/utils/__init__.py
finlab_guard/utils/exceptions.py
finlab_guard-0.4.1.dist-info/METADATA
finlab_guard-0.4.1.dist-info/WHEEL
finlab_guard-0.4.1.dist-info/licenses/LICENSE
finlab_guard-0.4.1.dist-info/RECORD
