Metadata-Version: 2.4
Name: finlab-guard
Version: 0.4.1
Summary: A lightweight package for managing local finlab data cache with versioning and time-context features
Author-email: iapcal <chiyimin2018@gmail.com>
License-Expression: MIT
License-File: LICENSE
Keywords: backtesting,cache,data,finlab,versioning
Classifier: Development Status :: 4 - Beta
Classifier: Intended Audience :: Developers
Classifier: License :: OSI Approved :: MIT License
Classifier: Programming Language :: Python :: 3
Classifier: Programming Language :: Python :: 3.9
Classifier: Programming Language :: Python :: 3.10
Classifier: Programming Language :: Python :: 3.11
Classifier: Programming Language :: Python :: 3.12
Classifier: Topic :: Office/Business :: Financial
Classifier: Topic :: Software Development :: Libraries :: Python Modules
Requires-Python: >=3.9
Requires-Dist: duckdb>=1.4.0
Requires-Dist: finlab>=1.2.23
Requires-Dist: numpy>=1.24.0
Requires-Dist: orjson>=3.11.3
Requires-Dist: pandas>=2.1.0
Requires-Dist: polars>=0.20.0
Requires-Dist: pyarrow>=10.0.0
Requires-Dist: tqdm>=4.66.0
Provides-Extra: dev
Requires-Dist: freezegun>=1.2.0; extra == 'dev'
Requires-Dist: mypy>=1.0.0; extra == 'dev'
Requires-Dist: pytest>=8.4.2; extra == 'dev'
Requires-Dist: ruff>=0.1.0; extra == 'dev'
